figma_mcp/__init__.py
figma_mcp/clean_node.py
figma_mcp/main.py
figma_mcp-0.1.2.dist-info/LICENSE
figma_mcp-0.1.2.dist-info/METADATA
figma_mcp-0.1.2.dist-info/WHEEL
figma_mcp-0.1.2.dist-info/entry_points.txt
figma_mcp-0.1.2.dist-info/top_level.txt
figma_mcp-0.1.2.dist-info/RECORD
