Metadata-Version: 2.2
Name: figma-mcp
Version: 0.1.2
Summary: Allow your AI coding agents to access figma files & prototypes directly
Author-email: Jason Zhou <jason.zhou.design@gmail.com>
License: MIT
Project-URL: Homepage, https://x.com/jasonzhou1993
Project-URL: Bug Tracker, https://x.com/jasonzhou1993
Classifier: Programming Language :: Python :: 3
Classifier: License :: OSI Approved :: MIT License
Classifier: Operating System :: OS Independent
Requires-Python: >=3.12
License-File: LICENSE
Requires-Dist: mcp[cli]>=1.3.0
Requires-Dist: python-dotenv>=1.0.1
Requires-Dist: requests>=2.32.3
